{
    "cameras": [
        {
            "color": {
                "calibrationIlluminant1": "D55",
                "cameraCalibration1": [
                    1.0,
                    0.0,
                    0.0,
                    0.0,
                    1.0,
                    0.0,
                    0.0,
                    0.0,
                    1.0
                ],
                "colorMatrix1": [
                    1.1741,
                    -0.2862,
                    -0.0448,
                    -0.1778,
                    0.9912,
                    0.2184,
                    0.0223,
                    0.2117,
                    0.532
                ]
            },
			"exposure": {
				"isoParameter": "iso",
				"isoAutoValue": "auto",
				"isoValues": [
					"auto",
					"50",
					"100",
					"200",
					"300",
					"400",
					"600",
					"800",
					"1000",
					"1200",
					"1400",
					"1600"
				],
				"shutterSpeedParameter": "set_shutter_speed",
				"shutterSpeedAutoValue": "0",
				"shutterSpeedValues": [
					"32s",
					"24s",
					"18s",
					"16s",
					"8s",
					"4s",
					"2s",
					"1s",
					"0",
					"2",
					"4",
					"8",
					"15",
					"30",
					"60",
					"125",
					"250",
					"500",
					"1000",
					"2000",
					"5000",
					"10000"
				]
			},
            "hasKnownMakernote": true,
            "id": 0,
            "isFrontCamera": false,
            "lens": {
                "aperture": 2.0
            },
            "name": "Asus ZenFone 2 ZE551ML (back camera)",
            "opcodes": [
                {
                    "opcodeList3File": "t4k37op3"
                }
            ],
            "retryOnError": false,
            "sensor": {
                "alignWidth": 256,
                "baseISO": 50,
                "bayerPattern": "GRBG",
                "binningRawImageSizes": [
                    {
                        "height": 1536,
                        "rawBufferAlignedWidth": 4352,
                        "rawBufferHeight": 1552,
                        "rawBufferLength": 6754304,
                        "rawBufferWidth": 2064,
                        "rawBufferWidthBytes": 4128,
                        "width": 2048
                    }
                ],
                "bitsPerPixel": 10,
                "blackLevel": [
                    64.0,
                    64.0,
                    64.0,
                    64.0
                ],
                "horizontalPadding": 16,
                "maker": "Toshiba",
                "name": "T4K37",
                "rawImageSizes": [
                    {
                        "height": 1536,
                        "rawBufferAlignedWidth": 4352,
                        "rawBufferHeight": 1552,
                        "rawBufferLength": 6754304,
                        "rawBufferWidth": 2064,
                        "rawBufferWidthBytes": 4128,
                        "width": 2048
                    },
                    {
                        "height": 2304,
                        "rawBufferAlignedWidth": 8448,
                        "rawBufferHeight": 2320,
                        "rawBufferLength": 19599360,
                        "rawBufferWidth": 4112,
                        "rawBufferWidthBytes": 8224,
                        "width": 4096
                    },
                    {
                        "height": 3072,
                        "rawBufferAlignedWidth": 8448,
                        "rawBufferHeight": 3088,
                        "rawBufferLength": 26087424,
                        "rawBufferWidth": 4112,
                        "rawBufferWidthBytes": 8224,
                        "width": 4096
                    }
                ],
                "storageBitsPerPixel": 16,
                "supportsPixelBinning": true,
                "verticalPadding": 16,
                "whiteLevel": 1023
            }
        },
        {
            "color": {
                "calibrationIlluminant1": "D55",
                "cameraCalibration1": [
                    1.0,
                    0.0,
                    0.0,
                    0.0,
                    1.0,
                    0.0,
                    0.0,
                    0.0,
                    1.0
                ],
                "colorMatrix1": [
                    0.9678,
                    -0.1981,
                    -0.0469,
                    -0.1948,
                    0.9686,
                    0.2657,
                    -0.0133,
                    0.2255,
                    0.6228
                ]
            },
			"exposure": {
				"isoParameter": "iso",
				"isoAutoValue": "auto",
				"isoValues": [
					"auto",
					"50",
					"100",
					"200",
					"300",
					"400",
					"600",
					"800",
					"1000",
					"1200",
					"1400",
					"1600"
				],
				"shutterSpeedParameter": "set_shutter_speed",
				"shutterSpeedAutoValue": "0",
				"shutterSpeedValues": [
					"2s",
					"1s",
					"0",
					"2",
					"4",
					"8",
					"15",
					"30",
					"60",
					"125",
					"250",
					"500",
					"1000",
					"2000",
					"5000",
					"10000"
				]
			},
            "hasKnownMakernote": true,
            "id": 1,
            "isFrontCamera": true,
            "lens": {
                "aperture": 2.0
            },
            "name": "Asus ZenFone 2 ZE551ML (front camera)",
            "opcodes": [
                {
                    "opcodeList3File": "ov5670op3"
                }
            ],
            "retryOnError": true,
            "sensor": {
                "alignWidth": 256,
                "baseISO": 50,
                "bayerPattern": "BGGR",
                "binningRawImageSizes": [],
                "bitsPerPixel": 10,
                "blackLevel": [
                    16.0,
                    16.0,
                    16.0,
                    16.0
                ],
                "horizontalPadding": 32,
                "maker": "OmniVision",
                "name": "OV5670",
                "rawImageSizes": [
                    {
                        "height": 1920,
                        "rawBufferAlignedWidth": 5376,
                        "rawBufferHeight": 1944,
                        "rawBufferLength": 10450944,
                        "rawBufferWidth": 2592,
                        "rawBufferWidthBytes": 5184,
                        "width": 2560
                    }
                ],
                "storageBitsPerPixel": 16,
                "supportsPixelBinning": false,
                "verticalPadding": 24,
                "whiteLevel": 1023
            }
        }
    ],
    "dumpDirectoryLocation": "/data/misc/media",
    "manufacturer": "Asus"
}